fpsensor/__init__.py
fpsensor/api.py
fpsensor/packet.py
fpsensor/sdk.py
fpsensor-0.2.6.dist-info/entry_points.txt
fpsensor-0.2.6.dist-info/WHEEL
fpsensor-0.2.6.dist-info/METADATA
fpsensor-0.2.6.dist-info/RECORD
