Metadata-Version: 2.1
Name: fpsensor
Version: 0.2.6
Summary: Python library for ZhianTec fingerprint sensors
Home-page: https://github.com/cwichel/fpsensor
License: MIT
Keywords: python,utilities
Author: Christian Wiche
Author-email: cwichel@gmail.com
Requires-Python: >=3.7,<4.0
Classifier: License :: OSI Approved :: MIT License
Classifier: Programming Language :: Python :: 3
Classifier: Programming Language :: Python :: 3.10
Classifier: Programming Language :: Python :: 3.7
Classifier: Programming Language :: Python :: 3.8
Classifier: Programming Language :: Python :: 3.9
Classifier: Topic :: Utilities
Requires-Dist: Pillow (>=8.3.0,<9.0.0)
Requires-Dist: embutils (>=0.8.0,<0.9.0)
